docs/conf.py
examples/customers/async.py
examples/customers/sync.py
examples/prices/async.py
examples/prices/sync.py
examples/products/async.py
examples/products/sync.py
paddle/__init__.py
paddle/client.py
paddle/environment.py
paddle/exceptions.py
paddle/aio/__init__.py
paddle/aio/client.py
paddle/extensions/__init__.py
paddle/extensions/webhooks.py
paddle/models/resources/__init__.py
paddle/models/resources/base.py
paddle/models/resources/customers.py
paddle/models/resources/prices.py
paddle/models/resources/products.py
paddle/models/resources/subscriptions.py
paddle/models/responses/__init__.py
paddle/models/responses/customers.py
paddle/models/responses/prices.py
paddle/models/responses/products.py
paddle/models/responses/shared.py
paddle/models/responses/subscriptions.py
paddle/utils/__init__.py
paddle/utils/constants.py
paddle/utils/decorators.py
paddle/utils/enums.py
paddle/utils/helpers.py
paddle/utils/request.py
paddle_sdk-0.1.6.dist-info/licenses/LICENSE
tests/conftest.py
tests/test_client.py
tests/test_decorators.py
tests/test_exceptions.py
tests/test_resources.py
tests/test_responses.py
tests/test_utils.py
paddle_sdk-0.1.6.dist-info/METADATA
paddle_sdk-0.1.6.dist-info/WHEEL
paddle_sdk-0.1.6.dist-info/top_level.txt
paddle_sdk-0.1.6.dist-info/RECORD
